{
	"$schema": "http://schema.management.azure.com/schemas/2015-01-01/deploymentTemplate.json#",
	"contentVersion": "1.0.0.0",
	"parameters": {
		"factoryName": {
			"type": "string",
			"metadata": "Data Factory name",
			"defaultValue": "toonedf"
		},
		"azuredatalakegen2_accountKey": {
			"type": "secureString",
			"metadata": "Secure string for 'accountKey' of 'azuredatalakegen2'"
		},
		"azuresqldatabase_connectionString": {
			"type": "secureString",
			"metadata": "Secure string for 'connectionString' of 'azuresqldatabase'"
		},
		"onpremisefilesystem_password": {
			"type": "secureString",
			"metadata": "Secure string for 'password' of 'onpremisefilesystem'"
		},
		"tooneadls2_accountKey": {
			"type": "secureString",
			"metadata": "Secure string for 'accountKey' of 'tooneadls2'"
		},
		"toonefilesystem_password": {
			"type": "secureString",
			"metadata": "Secure string for 'password' of 'toonefilesystem'"
		},
		"vmSqlServer_connectionString": {
			"type": "secureString",
			"metadata": "Secure string for 'connectionString' of 'vmSqlServer'"
		},
		"azuredatalakegen2_properties_typeProperties_url": {
			"type": "string",
			"defaultValue": "https://toonestorage02.dfs.core.windows.net"
		},
		"onpremisefilesystem_properties_typeProperties_host": {
			"type": "string",
			"defaultValue": "F:\\datafactoryDEMO"
		},
		"onpremisefilesystem_properties_typeProperties_userId": {
			"type": "string",
			"defaultValue": "admin_orange"
		},
		"tooneadls2_properties_typeProperties_url": {
			"type": "string",
			"defaultValue": "https://toonestorage02.dfs.core.windows.net"
		},
		"toonefilesystem_properties_typeProperties_host": {
			"type": "string",
			"defaultValue": "E:\\Data\\"
		},
		"toonefilesystem_properties_typeProperties_userId": {
			"type": "string",
			"defaultValue": "admin_orange"
		},
		"trigger_toone_01_properties_pipeline_parameters_FolderPath_Source": {
			"type": "string",
			"defaultValue": "E:\\"
		},
		"trigger_toone_01_properties_pipeline_parameters_Directory_Source": {
			"type": "string",
			"defaultValue": "Data"
		},
		"trigger_toone_01_properties_pipeline_parameters_FolderPath_Destination": {
			"type": "string",
			"defaultValue": "toonedatafactory"
		},
		"trigger_toone_01_properties_pipeline_parameters_Directory_Destination": {
			"type": "string",
			"defaultValue": "migrationdata"
		},
		"trigger_toone_01_properties_pipeline_parameters_LastModified_From": {
			"type": "string",
			"defaultValue": "@trigger (). outputs.windowStartTime"
		},
		"trigger_toone_01_properties_pipeline_parameters_LastModified_To": {
			"type": "string",
			"defaultValue": "@trigger (). outputs.windowEndTime"
		}
	},
	"variables": {
		"factoryId": "[concat('Microsoft.DataFactory/factories/', parameters('factoryName'))]"
	},
	"resources": [
		{
			"name": "[concat(parameters('factoryName'), '/CopyNewFilesByLastModifiedDate')]",
			"type": "Microsoft.DataFactory/factories/pipelines",
			"apiVersion": "2018-06-01",
			"properties": {
				"description": "Copy new and changed files only by using LastModifiedDate",
				"activities": [
					{
						"name": "CopyNewFiles",
						"description": "Copy new and changed files only by using LastModifiedDate",
						"type": "Copy",
						"dependsOn": [],
						"policy": {
							"timeout": "7.00:00:00",
							"retry": 0,
							"retryIntervalInSeconds": 30,
							"secureOutput": false,
							"secureInput": false
						},
						"userProperties": [],
						"typeProperties": {
							"source": {
								"type": "BinarySource",
								"storeSettings": {
									"type": "FileServerReadSettings",
									"recursive": true,
									"wildcardFileName": {
										"value": "*",
										"type": "Expression"
									},
									"modifiedDatetimeStart": {
										"value": "@{pipeline().parameters.LastModified_From}",
										"type": "Expression"
									},
									"modifiedDatetimeEnd": {
										"value": "@{pipeline().parameters.LastModified_To}",
										"type": "Expression"
									}
								}
							},
							"sink": {
								"type": "BinarySink",
								"storeSettings": {
									"type": "AzureBlobFSWriteSettings"
								}
							},
							"enableStaging": false
						},
						"inputs": [
							{
								"referenceName": "BinaryDataSourceStore",
								"type": "DatasetReference",
								"parameters": {
									"FolderPath": {
										"value": "@pipeline().parameters.FolderPath_Source",
										"type": "Expression"
									},
									"Directory": {
										"value": "@pipeline().parameters.Directory_Source",
										"type": "Expression"
									}
								}
							}
						],
						"outputs": [
							{
								"referenceName": "BinaryDataDestinationStore",
								"type": "DatasetReference",
								"parameters": {
									"Container": {
										"value": "@pipeline().parameters.FolderPath_Destination",
										"type": "Expression"
									},
									"Directory": {
										"value": "@pipeline().parameters.Directory_Destination",
										"type": "Expression"
									}
								}
							}
						]
					}
				],
				"parameters": {
					"FolderPath_Source": {
						"type": "String",
						"defaultValue": "sourcefolder"
					},
					"Directory_Source": {
						"type": "String",
						"defaultValue": "subfolder"
					},
					"FolderPath_Destination": {
						"type": "String",
						"defaultValue": "destinationfolder"
					},
					"Directory_Destination": {
						"type": "String",
						"defaultValue": "subfolder"
					},
					"LastModified_From": {
						"type": "String",
						"defaultValue": "2019-02-01T00:00:00Z"
					},
					"LastModified_To": {
						"type": "String",
						"defaultValue": "2019-03-01T00:00:00Z"
					}
				},
				"annotations": []
			},
			"dependsOn": [
				"[concat(variables('factoryId'), '/datasets/BinaryDataSourceStore')]",
				"[concat(variables('factoryId'), '/datasets/BinaryDataDestinationStore')]"
			]
		},
		{
			"name": "[concat(parameters('factoryName'), '/Demofileadsl2')]",
			"type": "Microsoft.DataFactory/factories/pipelines",
			"apiVersion": "2018-06-01",
			"properties": {
				"activities": [
					{
						"name": "Demomovefile",
						"type": "Copy",
						"dependsOn": [],
						"policy": {
							"timeout": "7.00:00:00",
							"retry": 0,
							"retryIntervalInSeconds": 30,
							"secureOutput": false,
							"secureInput": false
						},
						"userProperties": [],
						"typeProperties": {
							"source": {
								"type": "BinarySource",
								"storeSettings": {
									"type": "FileServerReadSettings",
									"recursive": true,
									"wildcardFileName": {
										"value": "*",
										"type": "Expression"
									},
									"modifiedDatetimeStart": {
										"value": "@{pipeline().parameters.LastModified_From}",
										"type": "Expression"
									},
									"modifiedDatetimeEnd": {
										"value": "@{pipeline().parameters.LastModified_To}",
										"type": "Expression"
									}
								}
							},
							"sink": {
								"type": "BinarySink",
								"storeSettings": {
									"type": "AzureBlobFSWriteSettings"
								}
							},
							"enableStaging": false
						},
						"inputs": [
							{
								"referenceName": "sourcebinary",
								"type": "DatasetReference",
								"parameters": {
									"FolderPath": {
										"value": "@pipeline().parameters.FolderPath_Source",
										"type": "Expression"
									},
									"Directory": {
										"value": "@pipeline().parameters.Directory_Source",
										"type": "Expression"
									}
								}
							}
						],
						"outputs": [
							{
								"referenceName": "sinkBinary",
								"type": "DatasetReference",
								"parameters": {
									"Container": {
										"value": "@pipeline().parameters.FolderPath_Destination",
										"type": "Expression"
									},
									"Directory": {
										"value": "@pipeline().parameters.Directory_Destination",
										"type": "Expression"
									}
								}
							}
						]
					}
				],
				"parameters": {
					"FolderPath_Source": {
						"type": "string",
						"defaultValue": "F:\\"
					},
					"Directory_Source": {
						"type": "string",
						"defaultValue": "datafactoryDEMO"
					},
					"FolderPath_Destination": {
						"type": "string",
						"defaultValue": "toonedatafactory"
					},
					"Directory_Destination": {
						"type": "string",
						"defaultValue": "demomigration"
					},
					"LastModified_From": {
						"type": "string",
						"defaultValue": "2019-02-01T00:00:00Z"
					},
					"LastModified_To": {
						"type": "string",
						"defaultValue": "2020-02-01T00:00:00Z"
					}
				},
				"annotations": []
			},
			"dependsOn": [
				"[concat(variables('factoryId'), '/datasets/sourcebinary')]",
				"[concat(variables('factoryId'), '/datasets/sinkBinary')]"
			]
		},
		{
			"name": "[concat(parameters('factoryName'), '/MoveFiles')]",
			"type": "Microsoft.DataFactory/factories/pipelines",
			"apiVersion": "2018-06-01",
			"properties": {
				"description": "Move files from one folder to another folder",
				"activities": [
					{
						"name": "GetFileList",
						"description": "Get the list of file",
						"type": "GetMetadata",
						"dependsOn": [],
						"policy": {
							"timeout": "7.00:00:00",
							"retry": 0,
							"retryIntervalInSeconds": 30,
							"secureOutput": false,
							"secureInput": false
						},
						"userProperties": [],
						"typeProperties": {
							"dataset": {
								"referenceName": "BinaryDataSource_Folder1",
								"type": "DatasetReference",
								"parameters": {
									"FolderPath": {
										"value": "@pipeline().parameters.SourceStore_Location",
										"type": "Expression"
									},
									"Directory": {
										"value": "@pipeline().parameters.SourceStore_Directory",
										"type": "Expression"
									}
								}
							},
							"fieldList": [
								"childItems"
							],
							"storeSettings": {
								"type": "FileServerReadSettings",
								"recursive": true
							}
						}
					},
					{
						"name": "ForEachFile",
						"description": "Iterate each file, and move them one by one.",
						"type": "ForEach",
						"dependsOn": [
							{
								"activity": "FilterFiles",
								"dependencyConditions": [
									"Succeeded"
								]
							}
						],
						"userProperties": [],
						"typeProperties": {
							"items": {
								"value": "@activity('FilterFiles').output.value",
								"type": "Expression"
							},
							"batchCount": 20,
							"activities": [
								{
									"name": "CopyAFile",
									"description": "Copy a file from the source store to the destination store.",
									"type": "Copy",
									"dependsOn": [],
									"policy": {
										"timeout": "7.00:00:00",
										"retry": 0,
										"retryIntervalInSeconds": 30,
										"secureOutput": false,
										"secureInput": false
									},
									"userProperties": [],
									"typeProperties": {
										"source": {
											"type": "BinarySource",
											"storeSettings": {
												"type": "FileServerReadSettings",
												"recursive": true
											},
											"recursive": false
										},
										"sink": {
											"type": "BinarySink",
											"storeSettings": {
												"type": "AzureBlobFSWriteSettings"
											}
										},
										"enableStaging": false,
										"dataIntegrationUnits": 0
									},
									"inputs": [
										{
											"referenceName": "BinaryDataSource_File1",
											"type": "DatasetReference",
											"parameters": {
												"FolderPath": {
													"value": "@pipeline().parameters.SourceStore_Location",
													"type": "Expression"
												},
												"Directory": {
													"value": "@pipeline().parameters.SourceStore_Directory",
													"type": "Expression"
												},
												"filename": {
													"value": "@item().name",
													"type": "Expression"
												}
											}
										}
									],
									"outputs": [
										{
											"referenceName": "BinaryDataDestination1",
											"type": "DatasetReference",
											"parameters": {
												"Container": {
													"value": "@pipeline().parameters.DestinationStore_Location",
													"type": "Expression"
												},
												"Directory": {
													"value": "@pipeline().parameters.DestinationStore_Directory",
													"type": "Expression"
												},
												"filename": {
													"value": "@item().name",
													"type": "Expression"
												}
											}
										}
									]
								},
								{
									"name": "DeleteAFile",
									"description": "Delete a file from the source store",
									"type": "Delete",
									"dependsOn": [
										{
											"activity": "CopyAFile",
											"dependencyConditions": [
												"Succeeded"
											]
										}
									],
									"policy": {
										"timeout": "7.00:00:00",
										"retry": 0,
										"retryIntervalInSeconds": 30,
										"secureOutput": false,
										"secureInput": false
									},
									"userProperties": [],
									"typeProperties": {
										"dataset": {
											"referenceName": "BinaryDataSource_File1",
											"type": "DatasetReference",
											"parameters": {
												"FolderPath": {
													"value": "@pipeline().parameters.SourceStore_Location",
													"type": "Expression"
												},
												"Directory": {
													"value": "@pipeline().parameters.SourceStore_Directory",
													"type": "Expression"
												},
												"filename": {
													"value": "@item().name",
													"type": "Expression"
												}
											}
										},
										"enableLogging": false,
										"storeSettings": {
											"type": "FileServerReadSettings",
											"recursive": true
										}
									}
								}
							]
						}
					},
					{
						"name": "FilterFiles",
						"description": "Only files will be selected, the source-folders will not be selected.",
						"type": "Filter",
						"dependsOn": [
							{
								"activity": "GetFileList",
								"dependencyConditions": [
									"Succeeded"
								]
							}
						],
						"userProperties": [],
						"typeProperties": {
							"items": {
								"value": "@activity('GetFileList').output.childItems",
								"type": "Expression"
							},
							"condition": {
								"value": "@equals(item().type, 'File')",
								"type": "Expression"
							}
						}
					}
				],
				"parameters": {
					"SourceStore_Location": {
						"type": "String"
					},
					"SourceStore_Directory": {
						"type": "String"
					},
					"DestinationStore_Location": {
						"type": "String"
					},
					"DestinationStore_Directory": {
						"type": "String"
					}
				},
				"annotations": []
			},
			"dependsOn": [
				"[concat(variables('factoryId'), '/datasets/BinaryDataSource_Folder1')]",
				"[concat(variables('factoryId'), '/datasets/BinaryDataSource_File1')]",
				"[concat(variables('factoryId'), '/datasets/BinaryDataDestination1')]"
			]
		},
		{
			"name": "[concat(parameters('factoryName'), '/AzureSqlTable1')]",
			"type": "Microsoft.DataFactory/factories/datasets",
			"apiVersion": "2018-06-01",
			"properties": {
				"linkedServiceName": {
					"referenceName": "azuresqldatabase",
					"type": "LinkedServiceReference"
				},
				"annotations": [],
				"type": "AzureSqlTable",
				"schema": [],
				"typeProperties": {}
			},
			"dependsOn": [
				"[concat(variables('factoryId'), '/linkedServices/azuresqldatabase')]"
			]
		},
		{
			"name": "[concat(parameters('factoryName'), '/BinaryDataDestination')]",
			"type": "Microsoft.DataFactory/factories/datasets",
			"apiVersion": "2018-06-01",
			"properties": {
				"description": "It describes the destination store.",
				"linkedServiceName": {
					"referenceName": "tooneadls2",
					"type": "LinkedServiceReference"
				},
				"parameters": {
					"Container": {
						"type": "String",
						"defaultValue": "toonedatafactory"
					},
					"Directory": {
						"type": "String",
						"defaultValue": "migrationdata"
					},
					"filename": {
						"type": "string"
					}
				},
				"annotations": [],
				"type": "Binary",
				"typeProperties": {
					"location": {
						"type": "AzureBlobFSLocation",
						"folderPath": {
							"value": "@{dataset().Directory}",
							"type": "Expression"
						},
						"fileSystem": {
							"value": "@{dataset().Container}",
							"type": "Expression"
						}
					}
				}
			},
			"dependsOn": [
				"[concat(variables('factoryId'), '/linkedServices/tooneadls2')]"
			]
		},
		{
			"name": "[concat(parameters('factoryName'), '/BinaryDataDestination1')]",
			"type": "Microsoft.DataFactory/factories/datasets",
			"apiVersion": "2018-06-01",
			"properties": {
				"description": "It describes the destination store.",
				"linkedServiceName": {
					"referenceName": "tooneadls2",
					"type": "LinkedServiceReference"
				},
				"parameters": {
					"Container": {
						"type": "String"
					},
					"Directory": {
						"type": "String"
					},
					"filename": {
						"type": "string"
					}
				},
				"annotations": [],
				"type": "Binary",
				"typeProperties": {
					"location": {
						"type": "AzureBlobFSLocation",
						"folderPath": {
							"value": "@{dataset().Directory}",
							"type": "Expression"
						},
						"fileSystem": {
							"value": "@{dataset().Container}",
							"type": "Expression"
						}
					}
				}
			},
			"dependsOn": [
				"[concat(variables('factoryId'), '/linkedServices/tooneadls2')]"
			]
		},
		{
			"name": "[concat(parameters('factoryName'), '/BinaryDataDestinationStore')]",
			"type": "Microsoft.DataFactory/factories/datasets",
			"apiVersion": "2018-06-01",
			"properties": {
				"description": "Connection to your data destination store.  ",
				"linkedServiceName": {
					"referenceName": "tooneadls2",
					"type": "LinkedServiceReference"
				},
				"parameters": {
					"Container": {
						"type": "string"
					},
					"Directory": {
						"type": "string"
					}
				},
				"annotations": [],
				"type": "Binary",
				"typeProperties": {
					"location": {
						"type": "AzureBlobFSLocation",
						"folderPath": {
							"value": "@dataset().Directory",
							"type": "Expression"
						},
						"fileSystem": {
							"value": "@dataset().Container",
							"type": "Expression"
						}
					}
				}
			},
			"dependsOn": [
				"[concat(variables('factoryId'), '/linkedServices/tooneadls2')]"
			]
		},
		{
			"name": "[concat(parameters('factoryName'), '/BinaryDataSourceStore')]",
			"type": "Microsoft.DataFactory/factories/datasets",
			"apiVersion": "2018-06-01",
			"properties": {
				"description": "Connection to your data source store. ",
				"linkedServiceName": {
					"referenceName": "toonefilesystem",
					"type": "LinkedServiceReference"
				},
				"parameters": {
					"FolderPath": {
						"type": "string"
					},
					"Directory": {
						"type": "string"
					}
				},
				"annotations": [],
				"type": "Binary",
				"typeProperties": {
					"location": {
						"type": "FileServerLocation",
						"folderPath": {
							"value": "@concat(dataset().FolderPath,'/',dataset().Directory)",
							"type": "Expression"
						}
					}
				}
			},
			"dependsOn": [
				"[concat(variables('factoryId'), '/linkedServices/toonefilesystem')]"
			]
		},
		{
			"name": "[concat(parameters('factoryName'), '/BinaryDataSource_File')]",
			"type": "Microsoft.DataFactory/factories/datasets",
			"apiVersion": "2018-06-01",
			"properties": {
				"description": "It describes the file in the data source store.",
				"linkedServiceName": {
					"referenceName": "toonefilesystem",
					"type": "LinkedServiceReference"
				},
				"parameters": {
					"FolderPath": {
						"type": "String"
					},
					"Directory": {
						"type": "String",
						"defaultValue": "source"
					},
					"filename": {
						"type": "string"
					}
				},
				"annotations": [],
				"type": "Binary",
				"typeProperties": {
					"location": {
						"type": "FileServerLocation",
						"fileName": {
							"value": "@dataset().filename",
							"type": "Expression"
						},
						"folderPath": {
							"value": "@concat(dataset().FolderPath,'/',dataset().Directory)",
							"type": "Expression"
						}
					}
				}
			},
			"dependsOn": [
				"[concat(variables('factoryId'), '/linkedServices/toonefilesystem')]"
			]
		},
		{
			"name": "[concat(parameters('factoryName'), '/BinaryDataSource_File1')]",
			"type": "Microsoft.DataFactory/factories/datasets",
			"apiVersion": "2018-06-01",
			"properties": {
				"description": "It describes the file in the data source store.",
				"linkedServiceName": {
					"referenceName": "toonefilesystem",
					"type": "LinkedServiceReference"
				},
				"parameters": {
					"FolderPath": {
						"type": "String"
					},
					"Directory": {
						"type": "String"
					},
					"filename": {
						"type": "string"
					}
				},
				"annotations": [],
				"type": "Binary",
				"typeProperties": {
					"location": {
						"type": "FileServerLocation",
						"fileName": {
							"value": "@dataset().filename",
							"type": "Expression"
						},
						"folderPath": {
							"value": "@concat(dataset().FolderPath,'/',dataset().Directory)",
							"type": "Expression"
						}
					}
				}
			},
			"dependsOn": [
				"[concat(variables('factoryId'), '/linkedServices/toonefilesystem')]"
			]
		},
		{
			"name": "[concat(parameters('factoryName'), '/BinaryDataSource_Folder')]",
			"type": "Microsoft.DataFactory/factories/datasets",
			"apiVersion": "2018-06-01",
			"properties": {
				"description": "It describes the folder in the data source store.",
				"linkedServiceName": {
					"referenceName": "toonefilesystem",
					"type": "LinkedServiceReference"
				},
				"parameters": {
					"FolderPath": {
						"type": "String"
					},
					"Directory": {
						"type": "String"
					}
				},
				"annotations": [],
				"type": "Binary",
				"typeProperties": {
					"location": {
						"type": "FileServerLocation",
						"folderPath": {
							"value": "@concat(dataset().FolderPath,'/',dataset().Directory)",
							"type": "Expression"
						}
					}
				}
			},
			"dependsOn": [
				"[concat(variables('factoryId'), '/linkedServices/toonefilesystem')]"
			]
		},
		{
			"name": "[concat(parameters('factoryName'), '/BinaryDataSource_Folder1')]",
			"type": "Microsoft.DataFactory/factories/datasets",
			"apiVersion": "2018-06-01",
			"properties": {
				"description": "It describes the folder in the data source store.",
				"linkedServiceName": {
					"referenceName": "toonefilesystem",
					"type": "LinkedServiceReference"
				},
				"parameters": {
					"FolderPath": {
						"type": "String"
					},
					"Directory": {
						"type": "String"
					}
				},
				"annotations": [],
				"type": "Binary",
				"typeProperties": {
					"location": {
						"type": "FileServerLocation",
						"folderPath": {
							"value": "@concat(dataset().FolderPath,'/',dataset().Directory)",
							"type": "Expression"
						}
					}
				}
			},
			"dependsOn": [
				"[concat(variables('factoryId'), '/linkedServices/toonefilesystem')]"
			]
		},
		{
			"name": "[concat(parameters('factoryName'), '/SqlServerTable1')]",
			"type": "Microsoft.DataFactory/factories/datasets",
			"apiVersion": "2018-06-01",
			"properties": {
				"linkedServiceName": {
					"referenceName": "vmSqlServer",
					"type": "LinkedServiceReference"
				},
				"annotations": [],
				"type": "SqlServerTable",
				"schema": [],
				"typeProperties": {}
			},
			"dependsOn": [
				"[concat(variables('factoryId'), '/linkedServices/vmSqlServer')]"
			]
		},
		{
			"name": "[concat(parameters('factoryName'), '/sinkBinary')]",
			"type": "Microsoft.DataFactory/factories/datasets",
			"apiVersion": "2018-06-01",
			"properties": {
				"linkedServiceName": {
					"referenceName": "azuredatalakegen2",
					"type": "LinkedServiceReference"
				},
				"parameters": {
					"Container": {
						"type": "string"
					},
					"Directory": {
						"type": "string"
					}
				},
				"annotations": [],
				"type": "Binary",
				"typeProperties": {
					"location": {
						"type": "AzureBlobFSLocation",
						"folderPath": {
							"value": "@dataset().Directory",
							"type": "Expression"
						},
						"fileSystem": {
							"value": "@dataset().Container",
							"type": "Expression"
						}
					}
				}
			},
			"dependsOn": [
				"[concat(variables('factoryId'), '/linkedServices/azuredatalakegen2')]"
			]
		},
		{
			"name": "[concat(parameters('factoryName'), '/sinktoonejson')]",
			"type": "Microsoft.DataFactory/factories/datasets",
			"apiVersion": "2018-06-01",
			"properties": {
				"linkedServiceName": {
					"referenceName": "tooneadls2",
					"type": "LinkedServiceReference"
				},
				"annotations": [],
				"type": "Json",
				"typeProperties": {
					"location": {
						"type": "AzureBlobFSLocation",
						"folderPath": "migrationdata",
						"fileSystem": "toonedatafactory"
					}
				},
				"schema": {}
			},
			"dependsOn": [
				"[concat(variables('factoryId'), '/linkedServices/tooneadls2')]"
			]
		},
		{
			"name": "[concat(parameters('factoryName'), '/sourcebinary')]",
			"type": "Microsoft.DataFactory/factories/datasets",
			"apiVersion": "2018-06-01",
			"properties": {
				"linkedServiceName": {
					"referenceName": "onpremisefilesystem",
					"type": "LinkedServiceReference"
				},
				"parameters": {
					"FolderPath": {
						"type": "string"
					},
					"Directory": {
						"type": "string"
					}
				},
				"annotations": [],
				"type": "Binary",
				"typeProperties": {
					"location": {
						"type": "FileServerLocation",
						"folderPath": {
							"value": "@concat(dataset().FolderPath,'/',dataset().Directory)",
							"type": "Expression"
						}
					}
				}
			},
			"dependsOn": [
				"[concat(variables('factoryId'), '/linkedServices/onpremisefilesystem')]"
			]
		},
		{
			"name": "[concat(parameters('factoryName'), '/sourcetoonejson')]",
			"type": "Microsoft.DataFactory/factories/datasets",
			"apiVersion": "2018-06-01",
			"properties": {
				"linkedServiceName": {
					"referenceName": "toonefilesystem",
					"type": "LinkedServiceReference"
				},
				"annotations": [],
				"type": "Json",
				"typeProperties": {
					"location": {
						"type": "FileServerLocation"
					}
				},
				"schema": {}
			},
			"dependsOn": [
				"[concat(variables('factoryId'), '/linkedServices/toonefilesystem')]"
			]
		},
		{
			"name": "[concat(parameters('factoryName'), '/azuredatalakegen2')]",
			"type": "Microsoft.DataFactory/factories/linkedServices",
			"apiVersion": "2018-06-01",
			"properties": {
				"annotations": [],
				"type": "AzureBlobFS",
				"typeProperties": {
					"url": "[parameters('azuredatalakegen2_properties_typeProperties_url')]",
					"accountKey": {
						"type": "SecureString",
						"value": "[parameters('azuredatalakegen2_accountKey')]"
					}
				}
			},
			"dependsOn": []
		},
		{
			"name": "[concat(parameters('factoryName'), '/azuresqldatabase')]",
			"type": "Microsoft.DataFactory/factories/linkedServices",
			"apiVersion": "2018-06-01",
			"properties": {
				"annotations": [],
				"type": "AzureSqlDatabase",
				"typeProperties": {
					"connectionString": "[parameters('azuresqldatabase_connectionString')]"
				}
			},
			"dependsOn": []
		},
		{
			"name": "[concat(parameters('factoryName'), '/onpremisefilesystem')]",
			"type": "Microsoft.DataFactory/factories/linkedServices",
			"apiVersion": "2018-06-01",
			"properties": {
				"annotations": [],
				"type": "FileServer",
				"typeProperties": {
					"host": "[parameters('onpremisefilesystem_properties_typeProperties_host')]",
					"userId": "[parameters('onpremisefilesystem_properties_typeProperties_userId')]",
					"password": {
						"type": "SecureString",
						"value": "[parameters('onpremisefilesystem_password')]"
					}
				},
				"connectVia": {
					"referenceName": "DemointegrationRuntime",
					"type": "IntegrationRuntimeReference"
				}
			},
			"dependsOn": [
				"[concat(variables('factoryId'), '/integrationRuntimes/DemointegrationRuntime')]"
			]
		},
		{
			"name": "[concat(parameters('factoryName'), '/tooneadls2')]",
			"type": "Microsoft.DataFactory/factories/linkedServices",
			"apiVersion": "2018-06-01",
			"properties": {
				"annotations": [],
				"type": "AzureBlobFS",
				"typeProperties": {
					"url": "[parameters('tooneadls2_properties_typeProperties_url')]",
					"accountKey": {
						"type": "SecureString",
						"value": "[parameters('tooneadls2_accountKey')]"
					}
				}
			},
			"dependsOn": []
		},
		{
			"name": "[concat(parameters('factoryName'), '/toonefilesystem')]",
			"type": "Microsoft.DataFactory/factories/linkedServices",
			"apiVersion": "2018-06-01",
			"properties": {
				"annotations": [],
				"type": "FileServer",
				"typeProperties": {
					"host": "[parameters('toonefilesystem_properties_typeProperties_host')]",
					"userId": "[parameters('toonefilesystem_properties_typeProperties_userId')]",
					"password": {
						"type": "SecureString",
						"value": "[parameters('toonefilesystem_password')]"
					}
				},
				"connectVia": {
					"referenceName": "tooneselfir",
					"type": "IntegrationRuntimeReference"
				}
			},
			"dependsOn": [
				"[concat(variables('factoryId'), '/integrationRuntimes/tooneselfir')]"
			]
		},
		{
			"name": "[concat(parameters('factoryName'), '/vmSqlServer')]",
			"type": "Microsoft.DataFactory/factories/linkedServices",
			"apiVersion": "2018-06-01",
			"properties": {
				"annotations": [],
				"type": "SqlServer",
				"typeProperties": {
					"connectionString": "[parameters('vmSqlServer_connectionString')]"
				}
			},
			"dependsOn": []
		},
		{
			"name": "[concat(parameters('factoryName'), '/trigger_toone_01')]",
			"type": "Microsoft.DataFactory/factories/triggers",
			"apiVersion": "2018-06-01",
			"properties": {
				"annotations": [],
				"runtimeState": "Stopped",
				"pipeline": {
					"pipelineReference": {
						"referenceName": "CopyNewFilesByLastModifiedDate",
						"type": "PipelineReference"
					},
					"parameters": {
						"FolderPath_Source": "[parameters('trigger_toone_01_properties_pipeline_parameters_FolderPath_Source')]",
						"Directory_Source": "[parameters('trigger_toone_01_properties_pipeline_parameters_Directory_Source')]",
						"FolderPath_Destination": "[parameters('trigger_toone_01_properties_pipeline_parameters_FolderPath_Destination')]",
						"Directory_Destination": "[parameters('trigger_toone_01_properties_pipeline_parameters_Directory_Destination')]",
						"LastModified_From": "[parameters('trigger_toone_01_properties_pipeline_parameters_LastModified_From')]",
						"LastModified_To": "[parameters('trigger_toone_01_properties_pipeline_parameters_LastModified_To')]"
					}
				},
				"type": "TumblingWindowTrigger",
				"typeProperties": {
					"frequency": "Minute",
					"interval": 15,
					"startTime": "2020-01-13T07:42:00.000Z",
					"delay": "00:00:00",
					"maxConcurrency": 50,
					"retryPolicy": {
						"intervalInSeconds": 30
					}
				}
			},
			"dependsOn": [
				"[concat(variables('factoryId'), '/pipelines/CopyNewFilesByLastModifiedDate')]"
			]
		},
		{
			"name": "[concat(parameters('factoryName'), '/DemointegrationRuntime')]",
			"type": "Microsoft.DataFactory/factories/integrationRuntimes",
			"apiVersion": "2018-06-01",
			"properties": {
				"type": "SelfHosted",
				"typeProperties": {}
			},
			"dependsOn": []
		},
		{
			"name": "[concat(parameters('factoryName'), '/tooneselfir')]",
			"type": "Microsoft.DataFactory/factories/integrationRuntimes",
			"apiVersion": "2018-06-01",
			"properties": {
				"type": "SelfHosted",
				"typeProperties": {}
			},
			"dependsOn": []
		},
		{
			"name": "[concat(parameters('factoryName'), '/demotrigger')]",
			"type": "Microsoft.DataFactory/factories/triggers",
			"apiVersion": "2018-06-01",
			"properties": {
				"annotations": [],
				"runtimeState": "Stopped",
				"type": "TumblingWindowTrigger",
				"typeProperties": {
					"frequency": "Minute",
					"interval": 15,
					"startTime": "2020-01-14T14:13:00.000Z",
					"delay": "00:00:00",
					"maxConcurrency": 50,
					"retryPolicy": {
						"intervalInSeconds": 30
					}
				}
			},
			"dependsOn": []
		}
	]
}